__init__.py
cli.py
charonfig-0.1.0.dist-info/METADATA
charonfig-0.1.0.dist-info/WHEEL
charonfig-0.1.0.dist-info/entry_points.txt
charonfig-0.1.0.dist-info/top_level.txt
charonfig-0.1.0.dist-info/RECORD
