Metadata-Version: 2.4
Name: charonfig
Version: 0.1.0
Summary: A flexible configuration management library with support for typed fields, encryption, and multiple formats.
Author-email: Alli Ayomide <allioladapo5@gmail.com>
License: MIT
Project-URL: Homepage, https://github.com/AAEO04/charonfig
Keywords: configuration,config,env,yaml,json,encryption
Classifier: Development Status :: 4 - Beta
Classifier: Intended Audience :: Developers
Classifier: Operating System :: OS Independent
Classifier: Programming Language :: Python :: 3
Classifier: Programming Language :: Python :: 3.8
Classifier: Programming Language :: Python :: 3.9
Classifier: Programming Language :: Python :: 3.10
Classifier: Programming Language :: Python :: 3.11
Classifier: Programming Language :: Python :: 3.12
Classifier: Topic :: Software Development :: Libraries :: Python Modules
Classifier: License :: OSI Approved :: MIT License
Requires-Python: >=3.8
Requires-Dist: cryptography>=3.4
Requires-Dist: PyYAML>=5.4
